thaifastembed-0.1.2.dist-info/METADATA
thaifastembed-0.1.2.dist-info/WHEEL
thaifastembed/__init__.py
thaifastembed/bm25.py
thaifastembed/sparse_embedding.py
thaifastembed/text_processor.py
thaifastembed/thaifastembed_rust.cpython-310-darwin.so
thaifastembed/types.py
thaifastembed-0.1.2.dist-info/RECORD
