Metadata-Version: 2.4
Name: thaifastembed
Version: 0.1.2
